.gitignore
.travis.yml
LICENSE
README.md
conftest.py
setup.cfg
setup.py
controlhost/__init__.py
controlhost/__version__.py
controlhost/controlhost.py
controlhost.egg-info/PKG-INFO
controlhost.egg-info/SOURCES.txt
controlhost.egg-info/dependency_links.txt
controlhost.egg-info/entry_points.txt
controlhost.egg-info/top_level.txt
controlhost/tests/__init__.py
controlhost/tests/test_controlhost.py
examples/client.py
examples/getmessage.py
examples/putmessage.py