Metadata-Version: 1.1
Name: controlhost
Version: 0.7
Summary: A set of classes and tools wich uses the ControlHost protocol.
Home-page: https://github.com/tamasgal/controlhost/
Author: Tamas Gal
Author-email: himself@tamasgal.com
License: UNKNOWN
Platform: any
Classifier: Development Status :: 3 - Alpha
Classifier: Intended Audience :: Developers
Classifier: Programming Language :: Python
